transfory/__init__.py
transfory/base.py
transfory/column_transformer.py
transfory/datetime.py
transfory/encoder.py
transfory/exceptions.py
transfory/featuregen.py
transfory/insight.py
transfory/missing.py
transfory/outlier.py
transfory/pipeline.py
transfory/scaler.py
transfory-1.3.0.dist-info/licenses/LICENSE
transfory-1.3.0.dist-info/METADATA
transfory-1.3.0.dist-info/WHEEL
transfory-1.3.0.dist-info/top_level.txt
transfory-1.3.0.dist-info/RECORD
