Metadata-Version: 2.4
Name: transfory
Version: 1.3.0
Summary: An Object-Oriented Data Transformation Toolkit
Author-email: MCQYP <mandamian.rogelioiii@gmail.com>
License: MIT
Project-URL: Homepage, https://github.com/Troge-dev/transfory
Project-URL: Bug Tracker, https://github.com/Troge-dev/transfory/issues
Classifier: Programming Language :: Python :: 3
Classifier: Operating System :: OS Independent
Classifier: Intended Audience :: Developers
Classifier: Intended Audience :: Science/Research
Classifier: Topic :: Software Development :: Libraries :: Python Modules
Classifier: Topic :: Scientific/Engineering :: Information Analysis
Requires-Python: >=3.8
License-File: LICENSE
Requires-Dist: pandas
Requires-Dist: numpy
Requires-Dist: scikit-learn
Requires-Dist: joblib
Dynamic: license-file
